oos/__init__.py
oos/_nbdev.py
oos/base.py
oos-0.0.2.dist-info/LICENSE
oos-0.0.2.dist-info/METADATA
oos-0.0.2.dist-info/WHEEL
oos-0.0.2.dist-info/entry_points.txt
oos-0.0.2.dist-info/top_level.txt
oos-0.0.2.dist-info/RECORD
