Metadata-Version: 2.1
Name: oos
Version: 0.0.2
Summary: A basic object-oriented programming framework for sports analysis
Home-page: https://github.com/armstrys/oos/tree/main/
Author: Ryan Armstrong
Author-email: armstrys@gmail.com
License: MIT License
Keywords: sports object-oreiented programming data analysis
Platform: UNKNOWN
Classifier: Development Status :: 2 - Pre-Alpha
Classifier: Intended Audience :: Developers
Classifier: Natural Language :: English
Classifier: Programming Language :: Python :: 3.6
Classifier: Programming Language :: Python :: 3.7
Classifier: Programming Language :: Python :: 3.8
Classifier: License :: OSI Approved :: MIT License
Requires-Python: >=3.6
License-File: LICENSE
Requires-Dist: pip
Requires-Dist: packaging
Requires-Dist: pandas
Provides-Extra: dev
